<Properties StartupConfiguration="{DD212917-5AE6-4D4C-89B9-F06E3F2CF646}|Default">
  <MonoDevelop.Ide.ItemProperties.Zoprna__sedmica PreferredExecutionTarget="MonoDevelop.Default" />
  <MonoDevelop.Ide.ItemProperties.Viva__La__Difference PreferredExecutionTarget="MonoDevelop.Default" />
  <MonoDevelop.Ide.Workbench ActiveDocument="Osamljeni_sumniki/Program.cs">
    <Files>
      <File FileName="Koliko_najvecjih/Program.cs" Line="68" Column="14" />
      <File FileName="Zoprna_sedmica/Program.cs" Line="84" Column="14" />
      <File FileName="Mnozimo_se/Program.cs" Line="58" Column="49" />
      <File FileName="Viva_La_Difference/Program.cs" Line="39" Column="18" />
      <File FileName="Osamljeni_sumniki/Program.cs" Line="37" Column="14" />
    </Files>
    <Pads>
      <Pad Id="ProjectPad">
        <State name="__root__">
          <Node name="Vaje_5" expanded="True">
            <Node name="Koliko_najvecjih" expanded="True" />
            <Node name="Mnozimo_se" expanded="True" />
            <Node name="Osamljeni_sumniki" expanded="True">
              <Node name="Program.cs" selected="True" />
            </Node>
            <Node name="Viva_La_Difference" expanded="True" />
            <Node name="Zoprna_sedmica" expanded="True" />
          </Node>
        </State>
      </Pad>
    </Pads>
  </MonoDevelop.Ide.Workbench>
  <MonoDevelop.Ide.ItemProperties.Mnozimo__se PreferredExecutionTarget="MonoDevelop.Default" />
  <MonoDevelop.Ide.ItemProperties.Osamljeni__sumniki PreferredExecutionTarget="MonoDevelop.Default" />
  <MonoDevelop.Ide.DebuggingService.PinnedWatches />
  <MonoDevelop.Ide.Workspace ActiveConfiguration="Debug" />
  <MonoDevelop.Ide.DebuggingService.Breakpoints>
    <BreakpointStore />
  </MonoDevelop.Ide.DebuggingService.Breakpoints>
  <MultiItemStartupConfigurations />
  <MonoDevelop.Ide.ItemProperties.Koliko__najvecjih PreferredExecutionTarget="MonoDevelop.Default" />
</Properties>